{
    "list": 
    [
        
{
    "id": 5020000,
"element": 2,
"hp": 2,
"dmg": 1,
"exp": 2,
"money": 50,
"speed": 5,
"imgsrc": "/Sprites/Enemy/5020000/",
"pivot": { "x": 0.5, "y": 0.0625 }
},

{
    "id": 5020001,
"element": 2,
"hp": 2,
"dmg": 1,
"exp": 2,
"money": 50,
"speed": 5,
"imgsrc": "/Sprites/Enemy/5020001/",
"pivot": { "x": 0.5, "y": 0.0625 }
},

{
    "id": 5020002,
"element": 2,
"hp": 2,
"dmg": 1,
"exp": 2,
"money": 50,
"speed": 5,
"imgsrc": "/Sprites/Enemy/5020002/",
"pivot": { "x": 0.5, "y": 0.0625 }
},

{
    "id": 5021002,
"element": 2,
"hp": 2,
"dmg": 1,
"exp": 2,
"money": 50,
"speed": 5,
"imgsrc": "/Sprites/Enemy/5021002/",
"pivot": { "x": 0.5, "y": 0.0625 }
},

{
    "id": 5021003,
"element": 2,
"hp": 2,
"dmg": 1,
"exp": 2,
"money": 50,
"speed": 5,
"imgsrc": "/Sprites/Enemy/5021003/",
"pivot": { "x": 0.5, "y": 0.0625 }
},

{
    "id": 5021004,
"element": 2,
"hp": 2,
"dmg": 1,
"exp": 2,
"money": 50,
"speed": 5,
"imgsrc": "/Sprites/Enemy/5021004/",
"pivot": { "x": 0.5, "y": 0.0625 }
},

{
    "id": 5022005,
"element": 2,
"hp": 2,
"dmg": 1,
"exp": 2,
"money": 50,
"speed": 5,
"imgsrc": "/Sprites/Enemy/5022005/",
"pivot": { "x": 0.5, "y": 0.0625 }
},

{
    "id": 5020100,
"element": 2,
"hp": 2,
"dmg": 1,
"exp": 2,
"money": 50,
"speed": 5,
"imgsrc": "/Sprites/Enemy/5020100/",
"pivot": { "x": 0.5, "y": 0.0625 }
},

{
    "id": 5020101,
"element": 2,
"hp": 2,
"dmg": 1,
"exp": 2,
"money": 50,
"speed": 5,
"imgsrc": "/Sprites/Enemy/5020101/",
"pivot": { "x": 0.5, "y": 0.0625 }
},

{
    "id": 5020102,
"element": 2,
"hp": 2,
"dmg": 1,
"exp": 2,
"money": 50,
"speed": 5,
"imgsrc": "/Sprites/Enemy/5020102/",
"pivot": { "x": 0.5, "y": 0.0625 }
},

{
    "id": 5021102,
"element": 2,
"hp": 2,
"dmg": 1,
"exp": 2,
"money": 50,
"speed": 5,
"imgsrc": "/Sprites/Enemy/5021102/",
"pivot": { "x": 0.5, "y": 0.0625 }
},

{
    "id": 5021103,
"element": 2,
"hp": 2,
"dmg": 1,
"exp": 2,
"money": 50,
"speed": 5,
"imgsrc": "/Sprites/Enemy/5021103/",
"pivot": { "x": 0.5, "y": 0.0625 }
},

{
    "id": 5021104,
"element": 2,
"hp": 2,
"dmg": 1,
"exp": 2,
"money": 50,
"speed": 5,
"imgsrc": "/Sprites/Enemy/5021104/",
"pivot": { "x": 0.5, "y": 0.0625 }
},

{
    "id": 5022105,
"element": 2,
"hp": 2,
"dmg": 1,
"exp": 2,
"money": 50,
"speed": 5,
"imgsrc": "/Sprites/Enemy/5022105/",
"pivot": { "x": 0.5, "y": 0.0625 }
}
    ]
}